cryptography/__init__.py
cryptography/py.typed
cryptography/fernet.py
cryptography/utils.py
cryptography/__about__.py
cryptography/exceptions.py
cryptography/x509/extensions.py
cryptography/x509/oid.py
cryptography/x509/__init__.py
cryptography/x509/ocsp.py
cryptography/x509/certificate_transparency.py
cryptography/x509/base.py
cryptography/x509/verification.py
cryptography/x509/name.py
cryptography/x509/general_name.py
cryptography/hazmat/__init__.py
cryptography/hazmat/_oid.py
cryptography/hazmat/backends/__init__.py
cryptography/hazmat/backends/openssl/aead.py
cryptography/hazmat/backends/openssl/__init__.py
cryptography/hazmat/backends/openssl/ciphers.py
cryptography/hazmat/backends/openssl/decode_asn1.py
cryptography/hazmat/backends/openssl/backend.py
cryptography/hazmat/bindings/__init__.py
cryptography/hazmat/bindings/_rust.abi3.so
cryptography/hazmat/bindings/_rust/x509.pyi
cryptography/hazmat/bindings/_rust/exceptions.pyi
cryptography/hazmat/bindings/_rust/_openssl.pyi
cryptography/hazmat/bindings/_rust/__init__.pyi
cryptography/hazmat/bindings/_rust/ocsp.pyi
cryptography/hazmat/bindings/_rust/asn1.pyi
cryptography/hazmat/bindings/_rust/pkcs7.pyi
cryptography/hazmat/bindings/_rust/openssl/hashes.pyi
cryptography/hazmat/bindings/_rust/openssl/poly1305.pyi
cryptography/hazmat/bindings/_rust/openssl/keys.pyi
cryptography/hazmat/bindings/_rust/openssl/ed448.pyi
cryptography/hazmat/bindings/_rust/openssl/x448.pyi
cryptography/hazmat/bindings/_rust/openssl/rsa.pyi
cryptography/hazmat/bindings/_rust/openssl/cmac.pyi
cryptography/hazmat/bindings/_rust/openssl/ec.pyi
cryptography/hazmat/bindings/_rust/openssl/aead.pyi
cryptography/hazmat/bindings/_rust/openssl/kdf.pyi
cryptography/hazmat/bindings/_rust/openssl/__init__.pyi
cryptography/hazmat/bindings/_rust/openssl/x25519.pyi
cryptography/hazmat/bindings/_rust/openssl/dh.pyi
cryptography/hazmat/bindings/_rust/openssl/dsa.pyi
cryptography-42.0.8.dist-info/LICENSE.APACHE
cryptography-42.0.8.dist-info/WHEEL
cryptography-42.0.8.dist-info/LICENSE.BSD
cryptography-42.0.8.dist-info/LICENSE
cryptography-42.0.8.dist-info/top_level.txt
cryptography-42.0.8.dist-info/RECORD
cryptography-42.0.8.dist-info/METADATA
