Metadata-Version: 2.1
Name: cryptography
Version: 42.0.8
Summary: cryptography is a package which provides cryptographic recipes and primitives to Python developers.
Author-email: The Python Cryptographic Authority and individual contributors <cryptography-dev@python.org>
License: Apache-2.0 OR BSD-3-Clause
Project-URL: homepage, https://github.com/pyca/cryptography
Project-URL: documentation, https://cryptography.io/
Project-URL: source, https://github.com/pyca/cryptography/
Project-URL: issues, https://github.com/pyca/cryptography/issues
Project-URL: changelog, https://cryptography.io/en/latest/changelog/
Classifier: Development Status :: 5 - Production/Stable
Classifier: Intended Audience :: Developers
Classifier: License :: OSI Approved :: Apache Software License
Classifier: License :: OSI Approved :: BSD License
Classifier: Natural Language :: English
Classifier: Operating System :: MacOS :: MacOS X
Classifier: Operating System :: POSIX
Classifier: Operating System :: POSIX :: BSD
Classifier: Operating System :: POSIX :: Linux
Classifier: Operating System :: Microsoft :: Windows
Classifier: Programming Language :: Python
Classifier: Programming Language :: Python :: 3
Classifier: Programming Language :: Python :: 3 :: Only
Classifier: Programming Language :: Python :: 3.7
Classifier: Programming Language :: Python :: 3.8
Classifier: Programming Language :: Python :: 3.9
Classifier: Programming Language :: Python :: 3.10
Classifier: Programming Language :: Python :: 3.11
Classifier: Programming Language :: Python :: 3.12
Classifier: Programming Language :: Python :: Implementation :: CPython
Classifier: Programming Language :: Python :: Implementation :: PyPy
Classifier: Topic :: Security :: Cryptography
Requires-Python: >=3.7
License-File: LICENSE
License-File: LICENSE.APACHE
License-File: LICENSE.BSD
Requires-Dist: cffi>=1.12; platform_python_implementation != "PyPy"
Provides-Extra: ssh
Requires-Dist: bcrypt>=3.1.5; extra == "ssh"
Provides-Extra: nox
Requires-Dist: nox; extra == "nox"
Provides-Extra: test
Requires-Dist: pytest>=6.2.0; extra == "test"
Requires-Dist: pytest-benchmark; extra == "test"
Requires-Dist: pytest-cov; extra == "test"
Requires-Dist: pytest-xdist; extra == "test"
Requires-Dist: pretend; extra == "test"
Requires-Dist: certifi; extra == "test"
Provides-Extra: test-randomorder
Requires-Dist: pytest-randomly; extra == "test-randomorder"
Provides-Extra: docs
Requires-Dist: sphinx>=5.3.0; extra == "docs"
Requires-Dist: sphinx-rtd-theme>=1.1.1; extra == "docs"
Provides-Extra: docstest
Requires-Dist: pyenchant>=1.6.11; extra == "docstest"
Requires-Dist: readme-renderer; extra == "docstest"
Requires-Dist: sphinxcontrib-spelling>=4.0.1; extra == "docstest"
Provides-Extra: sdist
Requires-Dist: build; extra == "sdist"
Provides-Extra: pep8test
Requires-Dist: ruff; extra == "pep8test"
Requires-Dist: mypy; extra == "pep8test"
Requires-Dist: check-sdist; extra == "pep8test"
Requires-Dist: click; extra == "pep8test"
